[{"Location":"Landingsveien 112, Oslo","ad_id":261449897,"ad_link":"https://www.finn.no/realestate/homes/ad.html?finnkode=261449897","ad_type":1,"energy_label":4,"from_year":1975,"lat":59.95346,"local_area_name":"Orebakken borettslag","lon":10.65059,"number_of_bedrooms":2,"owner_type_description":"Andel","property_type_description":"Leilighet","size_from":80,"to_year":1975,"type":"realestate"},{"Location":"Jon Alvssons gate 6, Skien","ad_id":261386090,"ad_link":"https://www.finn.no/realestate/homes/ad.html?finnkode=261386090","ad_type":1,"energy_label":4,"from_year":1975,"lat":59.19516,"local_area_name":"Bratsberg","lon":9.63078,"number_of_bedrooms":6,"owner_type_description":"Eier (Selveier)","property_type_description":"Enebolig","size_from":247,"to_year":1975,"type":"realestate"},{"Location":"Landingsveien 38, Oslo","ad_id":261035376,"ad_link":"https://www.finn.no/realestate/homes/ad.html?finnkode=261035376","ad_type":1,"energy_label":4,"from_year":1975,"lat":59.9527,"local_area_name":"RØA / VOKSEN SKOLE","lon":10.6548,"number_of_bedrooms":4,"owner_type_description":"Andel","property_type_description":"Leilighet","size_from":101,"to_year":1975,"type":"realestate"},{"Location":"Rollandslia 110, Ulset","ad_id":260944240,"ad_link":"https://www.finn.no/realestate/homes/ad.html?finnkode=260944240","ad_type":1,"energy_label":4,"from_year":1975,"lat":60.46014,"local_area_name":null,"lon":5.331,"number_of_bedrooms":3,"owner_type_description":"Andel","property_type_description":"Leilighet","size_from":97,"to_year":1975,"type":"realestate"},{"Location":"Tandbergvegen 100, Auli","ad_id":260437518,"ad_link":"https://www.finn.no/realestate/homes/ad.html?finnkode=260437518","ad_type":1,"energy_label":4,"from_year":1975,"lat":60.0278,"local_area_name":"Aulifeltet","lon":11.3601,"number_of_bedrooms":4,"owner_type_description":"Eier (Selveier)","property_type_description":"Enebolig","size_from":208,"to_year":1975,"type":"realestate"},{"Location":"Hektors vei 14C, Tønsberg","ad_id":260890823,"ad_link":"https://www.finn.no/realestate/homes/ad.html?finnkode=260890823","ad_type":1,"energy_label":4,"from_year":1975,"lat":59.2992,"local_area_name":"Tønsberg / Eik","lon":10.4177,"number_of_bedrooms":1,"owner_type_description":"Andel","property_type_description":"Rekkehus","size_from":55,"to_year":1975,"type":"realestate"},{"Location":"Bergtoras vei 19, Kristiansand S","ad_id":260712225,"ad_link":"https://www.finn.no/realestate/homes/ad.html?finnkode=260712225","ad_type":1,"energy_label":4,"from_year":1975,"lat":58.16795,"local_area_name":null,"lon":8.02722,"number_of_bedrooms":8,"owner_type_description":"Eier (Selveier)","property_type_description":"Enebolig","size_from":358,"to_year":1975,"type":"realestate"},{"Location":"Jonas Dahls vei 43, Oslo","ad_id":260433829,"ad_link":"https://www.finn.no/realestate/homes/ad.html?finnkode=260433829","ad_type":1,"energy_label":4,"from_year":1975,"lat":59.922,"local_area_name":"Ullern/Sollerud","lon":10.6422,"number_of_bedrooms":0,"owner_type_description":"Andel","property_type_description":"Leilighet","size_from":25,"to_year":1975,"type":"realestate"},{"Location":"Vågavegen 16, Florø","ad_id":229133159,"ad_link":"https://www.finn.no/realestate/homes/ad.html?finnkode=229133159","ad_type":1,"energy_label":4,"from_year":1975,"lat":61.5878,"local_area_name":null,"lon":5.0295,"number_of_bedrooms":6,"owner_type_description":"Eier (Selveier)","property_type_description":"Enebolig","size_from":188,"to_year":1975,"type":"realestate"},{"Location":"Vidars vei 17, Halden","ad_id":259749941,"ad_link":"https://www.finn.no/realestate/homes/ad.html?finnkode=259749941","ad_type":1,"energy_label":4,"from_year":1975,"lat":59.1342,"local_area_name":null,"lon":11.3732,"number_of_bedrooms":1,"owner_type_description":"Andel","property_type_description":"Leilighet","size_from":42,"to_year":1975,"type":"realestate"},{"Location":"Teglbakken 22, Alta","ad_id":228800468,"ad_link":"https://www.finn.no/realestate/homes/ad.html?finnkode=228800468","ad_type":1,"energy_label":4,"from_year":1975,"lat":69.96379,"local_area_name":null,"lon":23.40353,"number_of_bedrooms":6,"owner_type_description":"Eier (Selveier)","property_type_description":"Enebolig","size_from":204,"to_year":1975,"type":"realestate"}]