[{"Location":"Simensbråtveien 30, Oslo","ad_id":261444846,"ad_link":"https://www.finn.no/realestate/homes/ad.html?finnkode=261444846","ad_type":1,"energy_label":7,"from_year":1928,"lat":59.90046,"local_area_name":"Ekeberg / Simensbråten","lon":10.79238,"number_of_bedrooms":5,"owner_type_description":"Eier (Selveier)","property_type_description":"Enebolig","size_from":240,"to_year":1928,"type":"realestate"},{"Location":"Benneches gate 3A, Oslo","ad_id":261349799,"ad_link":"https://www.finn.no/realestate/homes/ad.html?finnkode=261349799","ad_type":1,"energy_label":7,"from_year":1928,"lat":59.92472,"local_area_name":"St. Hanshaugen / Bislett","lon":10.7368,"number_of_bedrooms":3,"owner_type_description":"Aksje","property_type_description":"Leilighet","size_from":122,"to_year":1928,"type":"realestate"},{"Location":"Skogstien 6, Oslo","ad_id":261014462,"ad_link":"https://www.finn.no/realestate/homes/ad.html?finnkode=261014462","ad_type":1,"energy_label":7,"from_year":1928,"lat":59.945,"local_area_name":"Sjelden mulighet på Høybråten","lon":10.93712,"number_of_bedrooms":5,"owner_type_description":"Eier (Selveier)","property_type_description":"Tomannsbolig","size_from":287,"to_year":1928,"type":"realestate"},{"Location":"Charlotte Andersens vei 7S, Oslo","ad_id":260912545,"ad_link":"https://www.finn.no/realestate/homes/ad.html?finnkode=260912545","ad_type":1,"energy_label":7,"from_year":1928,"lat":59.9425,"local_area_name":"Innerst i blindvei på Vinderen","lon":10.6978,"number_of_bedrooms":3,"owner_type_description":"Eier (Selveier)","property_type_description":"Leilighet","size_from":108,"to_year":1928,"type":"realestate"},{"Location":"Lindemans gate 5, Trondheim","ad_id":260969898,"ad_link":"https://www.finn.no/realestate/homes/ad.html?finnkode=260969898","ad_type":1,"energy_label":7,"from_year":1928,"lat":63.42844,"local_area_name":"ØVRE ROSENBORG/KUHAUGEN","lon":10.42522,"number_of_bedrooms":7,"owner_type_description":"Eier (Selveier)","property_type_description":"Tomannsbolig","size_from":209,"to_year":1928,"type":"realestate"},{"Location":"Larviksveien 51, Stavern","ad_id":260909085,"ad_link":"https://www.finn.no/realestate/homes/ad.html?finnkode=260909085","ad_type":1,"energy_label":7,"from_year":1928,"lat":59.0041,"local_area_name":"Stavern","lon":10.0341,"number_of_bedrooms":4,"owner_type_description":"Eier (Selveier)","property_type_description":"Enebolig","size_from":193,"to_year":1928,"type":"realestate"},{"Location":"Dukenveien 29C, Duken","ad_id":260931063,"ad_link":"https://www.finn.no/realestate/homes/ad.html?finnkode=260931063","ad_type":1,"energy_label":7,"from_year":1928,"lat":59.2127,"local_area_name":"NYHET!","lon":10.4551,"number_of_bedrooms":3,"owner_type_description":"Eier (Selveier)","property_type_description":"Enebolig","size_from":151,"to_year":1928,"type":"realestate"},{"Location":"Rossgutua 279, Skreia","ad_id":260911197,"ad_link":"https://www.finn.no/realestate/homes/ad.html?finnkode=260911197","ad_type":1,"energy_label":7,"from_year":1928,"lat":60.62828,"local_area_name":null,"lon":10.9377,"number_of_bedrooms":0,"owner_type_description":"Eier (Selveier)","property_type_description":"Enebolig","size_from":54,"to_year":1928,"type":"realestate"},{"Location":"Edvard Griegs vei 32, Bergen","ad_id":260700317,"ad_link":"https://www.finn.no/realestate/homes/ad.html?finnkode=260700317","ad_type":1,"energy_label":7,"from_year":1928,"lat":60.3756,"local_area_name":null,"lon":5.3465,"number_of_bedrooms":1,"owner_type_description":"Andel","property_type_description":"Leilighet","size_from":50,"to_year":1928,"type":"realestate"},{"Location":"Nedre Hagaveg 754, Årnes","ad_id":258710774,"ad_link":"https://www.finn.no/realestate/homes/ad.html?finnkode=258710774","ad_type":1,"energy_label":7,"from_year":1928,"lat":60.06962,"local_area_name":"Haga / Årnes","lon":11.39517,"number_of_bedrooms":2,"owner_type_description":"Eier (Selveier)","property_type_description":"Enebolig","size_from":85,"to_year":1928,"type":"realestate"},{"Location":"Overvikvegen 204, Selbu","ad_id":228005540,"ad_link":"https://www.finn.no/realestate/homes/ad.html?finnkode=228005540","ad_type":1,"energy_label":7,"from_year":1928,"lat":63.20461,"local_area_name":"Vikvarvet","lon":10.98628,"number_of_bedrooms":3,"owner_type_description":"Eier (Selveier)","property_type_description":"Enebolig","size_from":98,"to_year":1928,"type":"realestate"},{"Location":"Stalsberggata 8, Strømmen","ad_id":256092556,"ad_link":"https://www.finn.no/realestate/homes/ad.html?finnkode=256092556","ad_type":1,"energy_label":7,"from_year":1928,"lat":59.94495,"local_area_name":"Strømmen","lon":11.01297,"number_of_bedrooms":3,"owner_type_description":"Eier (Selveier)","property_type_description":"Enebolig","size_from":150,"to_year":1928,"type":"realestate"},{"Location":"Ankenesveien 220, Ankenes","ad_id":235402379,"ad_link":"https://www.finn.no/realestate/homes/ad.html?finnkode=235402379","ad_type":1,"energy_label":7,"from_year":1928,"lat":68.42209,"local_area_name":null,"lon":17.36872,"number_of_bedrooms":3,"owner_type_description":"Eier (Selveier)","property_type_description":"Enebolig","size_from":135,"to_year":1928,"type":"realestate"},{"Location":"Ekelyveien 4G, Oslo","ad_id":221405690,"ad_link":"https://www.finn.no/realestate/homes/ad.html?finnkode=221405690","ad_type":1,"energy_label":7,"from_year":1928,"lat":59.94533,"local_area_name":null,"lon":10.69785,"number_of_bedrooms":4,"owner_type_description":"Eier (Selveier)","property_type_description":"Enebolig","size_from":494,"to_year":1928,"type":"realestate"},{"Location":"Bjerkelundsveien 22, Jar","ad_id":259348558,"ad_link":"https://www.finn.no/realestate/homes/ad.html?finnkode=259348558","ad_type":1,"energy_label":7,"from_year":1928,"lat":59.92953,"local_area_name":"JAR","lon":10.61331,"number_of_bedrooms":3,"owner_type_description":"Eier (Selveier)","property_type_description":"Enebolig","size_from":197,"to_year":1928,"type":"realestate"},{"Location":"Sorenskrivervegen 18, Rælingen","ad_id":259344182,"ad_link":"https://www.finn.no/realestate/homes/ad.html?finnkode=259344182","ad_type":1,"energy_label":7,"from_year":1928,"lat":59.94903,"local_area_name":"Velkommen til Rælingen!","lon":11.03388,"number_of_bedrooms":3,"owner_type_description":"Eier (Selveier)","property_type_description":"Enebolig","size_from":178,"to_year":1928,"type":"realestate"},{"Location":"Nedre Møllenberg gate 60, Trondheim","ad_id":258716977,"ad_link":"https://www.finn.no/realestate/homes/ad.html?finnkode=258716977","ad_type":1,"energy_label":7,"from_year":1928,"lat":63.43306,"local_area_name":"Møllenberg","lon":10.41473,"number_of_bedrooms":1,"owner_type_description":"Eier (Selveier)","property_type_description":"Leilighet","size_from":56,"to_year":1928,"type":"realestate"},{"Location":"Ringgata 26, Ålesund","ad_id":219351342,"ad_link":"https://www.finn.no/realestate/homes/ad.html?finnkode=219351342","ad_type":1,"energy_label":7,"from_year":1928,"lat":62.46915,"local_area_name":"Aspøya","lon":6.12417,"number_of_bedrooms":3,"owner_type_description":"Eier (Selveier)","property_type_description":"Enebolig","size_from":139,"to_year":1928,"type":"realestate"},{"Location":"Berget 13, Flekkefjord","ad_id":196348179,"ad_link":"https://www.finn.no/realestate/homes/ad.html?finnkode=196348179","ad_type":1,"energy_label":7,"from_year":1928,"lat":58.2984,"local_area_name":"Sentrum","lon":6.6589,"number_of_bedrooms":2,"owner_type_description":"Eier (Selveier)","property_type_description":"Enebolig","size_from":123,"to_year":1928,"type":"realestate"},{"Location":"Eitrheimsvegen 49, Odda","ad_id":209206956,"ad_link":"https://www.finn.no/realestate/homes/ad.html?finnkode=209206956","ad_type":1,"energy_label":7,"from_year":1928,"lat":60.07089,"local_area_name":"Odda","lon":6.54017,"number_of_bedrooms":5,"owner_type_description":"Eier (Selveier)","property_type_description":"Enebolig","size_from":184,"to_year":1928,"type":"realestate"},{"Location":"Villastrøket 1, Vik i Sogn","ad_id":249137591,"ad_link":"https://www.finn.no/realestate/homes/ad.html?finnkode=249137591","ad_type":1,"energy_label":7,"from_year":1928,"lat":61.0858,"local_area_name":null,"lon":6.5794,"number_of_bedrooms":4,"owner_type_description":"Eier (Selveier)","property_type_description":"Enebolig","size_from":138,"to_year":1928,"type":"realestate"}]